<?xml version="1.0" encoding="utf-8" ?>
<dwsync>
<file name="09-GVC(6x7)-1-corr.jpg" server="ftpperso.free.fr/" local="129064772281790112" remote="129064742400000000" Dst="-1" />
<file name="10-GVC-1-gde-0k.jpg" server="ftpperso.free.fr/" local="129064772281802612" remote="129064742400000000" Dst="-1" />
<file name="11-corr.jpg" server="ftpperso.free.fr/" local="129064772281827613" remote="129064742400000000" Dst="-1" />
<file name="11-GVC(6x7)-2-corr.jpg" server="ftpperso.free.fr/" local="129064772281840113" remote="129064742400000000" Dst="-1" />
<file name="12-GVC(6x7)-4-corr.jpg" server="ftpperso.free.fr/" local="129064772281865113" remote="129064742400000000" Dst="-1" />
<file name="14-Demigny4-ok.jpg" server="ftpperso.free.fr/" local="129064772281877614" remote="129064742400000000" Dst="-1" />
<file name="15-Demigny1-ok.jpg" server="ftpperso.free.fr/" local="129064772281902614" remote="129064742400000000" Dst="-1" />
<file name="16-Demigny6-corr.jpg" server="ftpperso.free.fr/" local="129064772281915114" remote="129064742400000000" Dst="-1" />
<file name="17-Demigny-car+long-cor.jpg" server="ftpperso.free.fr/" local="129064772281940115" remote="129064742400000000" Dst="-1" />
<file name="Agi.jpg" server="ftpperso.free.fr/" local="129064772281952615" remote="129064742400000000" Dst="-1" />
<file name="09-GVC(6x7)-1-corr.jpg" server="ftpperso.free.fr" local="131403168000000000" remote="131403168000000000" Dst="1" />
<file name="10-GVC-1-gde-0k.jpg" server="ftpperso.free.fr" local="131403168000000000" remote="131403168000000000" Dst="1" />
<file name="11-corr.jpg" server="ftpperso.free.fr" local="131403168000000000" remote="131403168000000000" Dst="1" />
<file name="11-GVC(6x7)-2-corr.jpg" server="ftpperso.free.fr" local="131403168000000000" remote="131403168000000000" Dst="1" />
<file name="12-GVC(6x7)-4-corr.jpg" server="ftpperso.free.fr" local="131403168000000000" remote="131403168000000000" Dst="1" />
<file name="14-Demigny4-ok.jpg" server="ftpperso.free.fr" local="131403168000000000" remote="131403168000000000" Dst="1" />
<file name="15-Demigny1-ok.jpg" server="ftpperso.free.fr" local="131403168000000000" remote="131403168000000000" Dst="1" />
<file name="16-Demigny6-corr.jpg" server="ftpperso.free.fr" local="131403168000000000" remote="131403168000000000" Dst="1" />
<file name="17-Demigny-car+long-cor.jpg" server="ftpperso.free.fr" local="131403168000000000" remote="131403168000000000" Dst="1" />
<file name="Agi.jpg" server="ftpperso.free.fr" local="131403168000000000" remote="131403168000000000" Dst="1" />
<file name="09-GVC(6x7)-1-corr.jpg" server="perrodin.free.fr" local="129064772281790112" remote="130940545800000000" Dst="1" />
<file name="10-GVC-1-gde-0k.jpg" server="perrodin.free.fr" local="129064772281802612" remote="130940545800000000" Dst="1" />
<file name="11-corr.jpg" server="perrodin.free.fr" local="129064772281827613" remote="130940545800000000" Dst="1" />
<file name="11-GVC(6x7)-2-corr.jpg" server="perrodin.free.fr" local="129064772281840113" remote="130940545800000000" Dst="1" />
<file name="12-GVC(6x7)-4-corr.jpg" server="perrodin.free.fr" local="129064772281865113" remote="130940545800000000" Dst="1" />
<file name="14-Demigny4-ok.jpg" server="perrodin.free.fr" local="129064772281877614" remote="130940545800000000" Dst="1" />
<file name="15-Demigny1-ok.jpg" server="perrodin.free.fr" local="129064772281902614" remote="130940545800000000" Dst="1" />
<file name="16-Demigny6-corr.jpg" server="perrodin.free.fr" local="129064772281915114" remote="130940545800000000" Dst="1" />
<file name="17-Demigny-car+long-cor.jpg" server="perrodin.free.fr" local="129064772281940115" remote="130940545800000000" Dst="1" />
<file name="Agi.jpg" server="perrodin.free.fr" local="129064772281952615" remote="130940545800000000" Dst="1" />
</dwsync>